mausignald/__init__.py
mausignald/errors.py
mausignald/rpc.py
mausignald/signald.py
mausignald/types.py
mautrix_signal/__init__.py
mautrix_signal/__main__.py
mautrix_signal/config.py
mautrix_signal/example-config.yaml
mautrix_signal/formatter.py
mautrix_signal/get_version.py
mautrix_signal/matrix.py
mautrix_signal/portal.py
mautrix_signal/puppet.py
mautrix_signal/signal.py
mautrix_signal/user.py
mautrix_signal/version.py
mautrix_signal/commands/__init__.py
mautrix_signal/commands/auth.py
mautrix_signal/commands/conn.py
mautrix_signal/commands/signal.py
mautrix_signal/commands/typehint.py
mautrix_signal/commands/util.py
mautrix_signal/db/__init__.py
mautrix_signal/db/disappearing_message.py
mautrix_signal/db/message.py
mautrix_signal/db/portal.py
mautrix_signal/db/puppet.py
mautrix_signal/db/reaction.py
mautrix_signal/db/user.py
mautrix_signal/db/util.py
mautrix_signal/db/upgrade/__init__.py
mautrix_signal/db/upgrade/v00_latest_revision.py
mautrix_signal/db/upgrade/v02_portal_avatar_info.py
mautrix_signal/db/upgrade/v03_puppet_base_url.py
mautrix_signal/db/upgrade/v04_phone_sender_identifier.py
mautrix_signal/db/upgrade/v05_puppet_avatar_info.py
mautrix_signal/db/upgrade/v06_portal_revision.py
mautrix_signal/db/upgrade/v07_portal_relay_user.py
mautrix_signal/db/upgrade/v08_disappearing_messages.py
mautrix_signal/db/upgrade/v09_group_topic.py
mautrix_signal/db/upgrade/v10_puppet_name_quality.py
mautrix_signal/db/upgrade/v11_drop_number_support.py
mautrix_signal/db/upgrade/v12_add_contact_info_to_puppet.py
mautrix_signal/util/__init__.py
mautrix_signal/util/color_log.py
mautrix_signal/util/normalize_number.py
mautrix_signal/util/user_has_power_level.py
mautrix_signal/web/__init__.py
mautrix_signal/web/provisioning_api.py
mautrix_signal/web/segment_analytics.py
mautrix_signal-0.4.3.data/data/example-config.yaml
mautrix_signal-0.4.3.dist-info/LICENSE
mautrix_signal-0.4.3.dist-info/METADATA
mautrix_signal-0.4.3.dist-info/WHEEL
mautrix_signal-0.4.3.dist-info/top_level.txt
mautrix_signal-0.4.3.dist-info/RECORD
