Metadata-Version: 2.1
Name: mautrix-signal
Version: 0.4.3
Summary: A Matrix-Signal puppeting bridge.
Home-page: https://github.com/mautrix/signal
Author: Tulir Asokan
Author-email: tulir@maunium.net
Project-URL: Changelog, https://github.com/mautrix/signal/blob/master/CHANGELOG.md
Classifier: Development Status :: 4 - Beta
Classifier: License :: OSI Approved :: GNU Affero General Public License v3 or later (AGPLv3+)
Classifier: Topic :: Communications :: Chat
Classifier: Framework :: AsyncIO
Classifier: Programming Language :: Python
Classifier: Programming Language :: Python :: 3
Classifier: Programming Language :: Python :: 3.8
Classifier: Programming Language :: Python :: 3.9
Classifier: Programming Language :: Python :: 3.10
Requires-Python: ~=3.8
License-File: LICENSE
Requires-Dist: aiohttp (<4,>=3)
Requires-Dist: asyncpg (<0.28,>=0.20)
Requires-Dist: attrs (>=19.1)
Requires-Dist: commonmark (<0.10,>=0.8)
Requires-Dist: mautrix (<0.20,>=0.19.14)
Requires-Dist: python-magic (<0.5,>=0.4)
Requires-Dist: ruamel.yaml (<0.18,>=0.15.35)
Requires-Dist: yarl (<2,>=1)
Provides-Extra: all
Requires-Dist: Pillow (<10,>=4) ; extra == 'all'
Requires-Dist: aiosqlite (<0.20,>=0.16) ; extra == 'all'
Requires-Dist: phonenumbers (<9,>=8) ; extra == 'all'
Requires-Dist: prometheus-client (<0.17,>=0.6) ; extra == 'all'
Requires-Dist: pycryptodome (<4,>=3) ; extra == 'all'
Requires-Dist: python-olm (<4,>=3) ; extra == 'all'
Requires-Dist: qrcode (<8,>=6) ; extra == 'all'
Requires-Dist: signalstickers-client (<4,>=3) ; extra == 'all'
Requires-Dist: unpaddedbase64 (<3,>=1) ; extra == 'all'
Provides-Extra: e2be
Requires-Dist: pycryptodome (<4,>=3) ; extra == 'e2be'
Requires-Dist: python-olm (<4,>=3) ; extra == 'e2be'
Requires-Dist: unpaddedbase64 (<3,>=1) ; extra == 'e2be'
Provides-Extra: formattednumbers
Requires-Dist: phonenumbers (<9,>=8) ; extra == 'formattednumbers'
Provides-Extra: metrics
Requires-Dist: prometheus-client (<0.17,>=0.6) ; extra == 'metrics'
Provides-Extra: qrlink
Requires-Dist: Pillow (<10,>=4) ; extra == 'qrlink'
Requires-Dist: qrcode (<8,>=6) ; extra == 'qrlink'
Provides-Extra: sqlite
Requires-Dist: aiosqlite (<0.20,>=0.16) ; extra == 'sqlite'
Provides-Extra: stickers
Requires-Dist: signalstickers-client (<4,>=3) ; extra == 'stickers'
